denovo/__init__.py
denovo/core/configuration.py
denovo/core/containers.py
denovo/core/filing.py
denovo/core/framework.py
denovo/core/quirks.py
denovo/core/structures.py
denovo/utilities/__init__.py
denovo/utilities/decorators.py
denovo/utilities/lazy.py
denovo/utilities/memory.py
denovo/utilities/summary.py
denovo/utilities/testing.py
denovo/utilities/tools.py
denovo-0.1.0.dist-info/LICENSE
denovo-0.1.0.dist-info/WHEEL
denovo-0.1.0.dist-info/METADATA
denovo-0.1.0.dist-info/RECORD
